.gitignore
MANIFEST.in
setup.py
sxm/__init__.py
sxm/app.py
sxm/node.py
sxm/runnode.py
sxm/api/__init__.py
sxm/api/announce.py
sxm/api/auth.py
sxm/api/core.py
sxm/api/events.py
sxm/api/gallery.py
sxm/api/media.py
sxm/api/settings.py
sxm/api/text.py
sxm_signagenode.egg-info/PKG-INFO
sxm_signagenode.egg-info/SOURCES.txt
sxm_signagenode.egg-info/dependency_links.txt
sxm_signagenode.egg-info/entry_points.txt
sxm_signagenode.egg-info/requires.txt
sxm_signagenode.egg-info/top_level.txt